cbio_py/__init__.py
cbio_py/cbio_mod.py
cbio_py-0.1.4.dist-info/LICENSE
cbio_py-0.1.4.dist-info/METADATA
cbio_py-0.1.4.dist-info/WHEEL
cbio_py-0.1.4.dist-info/top_level.txt
cbio_py-0.1.4.dist-info/RECORD
