Metadata-Version: 2.1
Name: cbio-py
Version: 0.1.4
Summary: This is a python client for the cBioPortal API
Home-page: https://github.com/odagayev/cancer_module_cbio
Author: Sasha Dagayev
Project-URL: Bug Tracker, https://github.com/odagayev/cancer_module_cbio/issues
Classifier: Programming Language :: Python :: 3
Classifier: License :: OSI Approved :: MIT License
Classifier: Operating System :: OS Independent
Requires-Python: >=3.6
License-File: LICENSE
Requires-Dist: bravado (>11.0.0)
